july/__init__.py
july/colormaps.py
july/helpers.py
july/plot.py
july/rcmod.py
july/utils.py
july-0.1.3.dist-info/LICENSE
july-0.1.3.dist-info/METADATA
july-0.1.3.dist-info/WHEEL
july-0.1.3.dist-info/top_level.txt
july-0.1.3.dist-info/RECORD
