Metadata-Version: 2.1
Name: july
Version: 0.1.3
Summary: A small library for creating pretty heatmaps of daily data.
Home-page: https://github.com/e-hulten/july/
Author: Edvard Hultén
Author-email: edvard.hulten@gmail.com
License: MIT
Keywords: heatmap,visualisation,calendar,daily,matplotlib,github plot,month plot,date plot,plot,plotting
Platform: UNKNOWN
Classifier: Topic :: Scientific/Engineering :: Visualization
Classifier: Programming Language :: Python :: 3
Classifier: License :: OSI Approved :: MIT License
Classifier: Operating System :: OS Independent
Requires-Python: >=3.6
